diu/__init__.py
diu/main.py
diu/merge.py
diu/updater.py
docker_image_updater-1.0.0.dist-info/DESCRIPTION.rst
docker_image_updater-1.0.0.dist-info/METADATA
docker_image_updater-1.0.0.dist-info/RECORD
docker_image_updater-1.0.0.dist-info/WHEEL
docker_image_updater-1.0.0.dist-info/entry_points.txt
docker_image_updater-1.0.0.dist-info/metadata.json
docker_image_updater-1.0.0.dist-info/top_level.txt
