Metadata-Version: 2.0
Name: docker-image-updater
Version: 1.0.0
Summary: Update docker images and trigger commands in response to updates
Home-page: https://github.com/zoni/docker-image-updater
Author: Nick Groenen
Author-email: nick@groenen.me
License: MIT
Keywords: docker image update container
Platform: UNKNOWN
Classifier: Development Status :: 5 - Production/Stable
Classifier: Topic :: Utilities
Classifier: Topic :: System :: Systems Administration
Classifier: Intended Audience :: System Administrators
Classifier: License :: OSI Approved :: MIT License
Classifier: Operating System :: POSIX
Classifier: Programming Language :: Python :: 2.7
Classifier: Programming Language :: Python :: 3
Requires-Dist: attrs (>=15.0.0a1)
Requires-Dist: colorlog
Requires-Dist: docker-py
Requires-Dist: pyyaml
